tracker/__init__.py
tracker/apps.py
tracker/celery.py
tracker/conf.py
tracker/exceptions.py
tracker/signals.py
tracker/urls.py
tracker/admin/__init__.py
tracker/admin/candidate_ranking.py
tracker/admin/person.py
tracker/bin/candidates.csv
tracker/bin/candidate-images/Amy-Klobuchar-Color.png
tracker/bin/candidate-images/Andrew-Cuomo-Color.png
tracker/bin/candidate-images/Bernie-Sanders-Color.png
tracker/bin/candidate-images/Beto-Orourke-Color.png
tracker/bin/candidate-images/Cory-Booker-Color.png
tracker/bin/candidate-images/Deval-Patrick-Color.png
tracker/bin/candidate-images/Elizabeth-Warren-Color.png
tracker/bin/candidate-images/Eric-Garcetti-Color.png
tracker/bin/candidate-images/Eric-Holder-Color.png
tracker/bin/candidate-images/Eric-Swalwell-Color.png
tracker/bin/candidate-images/Hillary-Clinton-Color.png
tracker/bin/candidate-images/Howard-Schultz-Color.png
tracker/bin/candidate-images/Jay-Inslee-Color.png
tracker/bin/candidate-images/Jeff-Merkley-Color.png
tracker/bin/candidate-images/Joe-Biden-Color.png
tracker/bin/candidate-images/Joe-Kennedy-Color.png
tracker/bin/candidate-images/John-Delaney-Color.png
tracker/bin/candidate-images/John-Hickenlooper-Color.png
tracker/bin/candidate-images/John-Kerry-Color.png
tracker/bin/candidate-images/Julian-Castro-Color.png
tracker/bin/candidate-images/Kamala-Harris-Color.png
tracker/bin/candidate-images/Kirsten-Gillibrand-Color.png
tracker/bin/candidate-images/Mark-Cuban-Color.png
tracker/bin/candidate-images/Mark-Warner-Color.png
tracker/bin/candidate-images/Martin-Omalley-Color.png
tracker/bin/candidate-images/Michael-Avenatti-Color.png
tracker/bin/candidate-images/Michael-Bloomberg-Color.png
tracker/bin/candidate-images/Mitch-Landrieu-Color.png
tracker/bin/candidate-images/Pete-Buttigieg-Color.png
tracker/bin/candidate-images/Richard-Ojeda-Color.png
tracker/bin/candidate-images/Seth-Moulton-Color.png
tracker/bin/candidate-images/Sherrod-Brown-Color.png
tracker/bin/candidate-images/Steve-Bullock-Color.png
politico_civic_campaign_tracker-0.4.4.dist-info/LICENSE
politico_civic_campaign_tracker-0.4.4.dist-info/METADATA
politico_civic_campaign_tracker-0.4.4.dist-info/WHEEL
politico_civic_campaign_tracker-0.4.4.dist-info/top_level.txt
politico_civic_campaign_tracker-0.4.4.dist-info/RECORD
