Metadata-Version: 2.1
Name: politico-civic-campaign-tracker
Version: 0.4.4
Summary: UNKNOWN
Home-page: https://github.com/The-Politico/politico-civic-campaign-tracker
Author: POLITICO interactive news
Author-email: interactives@politico.com
License: MIT
Platform: UNKNOWN
Classifier: Development Status :: 3 - Alpha
Classifier: Framework :: Django
Classifier: Framework :: Django :: 2.0
Classifier: Intended Audience :: Developers
Classifier: Intended Audience :: Information Technology
Classifier: License :: OSI Approved :: MIT License
Classifier: Operating System :: OS Independent
Classifier: Programming Language :: Python :: 3
Classifier: Programming Language :: Python :: 3.5
Classifier: Programming Language :: Python :: 3.6
Classifier: Topic :: Internet :: WWW/HTTP
Requires-Dist: celery
Requires-Dist: django-cors-headers
Requires-Dist: django
Requires-Dist: django-nested-admin
Requires-Dist: djangorestframework
Requires-Dist: dj-database-url
Requires-Dist: politico-civic-entity
Requires-Dist: politico-civic-geography
Requires-Dist: politico-civic-government
Requires-Dist: politico-civic-election
Requires-Dist: politico-civic-biography
Requires-Dist: politico-civic-campaign
Requires-Dist: psycopg2
Requires-Dist: requests
Requires-Dist: python-twitter
Requires-Dist: webpreview
Provides-Extra: test
Requires-Dist: pytest ; extra == 'test'
